MANIFEST.in
README.md
setup.cfg
setup.py
version_module_B.py
module_B.egg-info/PKG-INFO
module_B.egg-info/SOURCES.txt
module_B.egg-info/dependency_links.txt
module_B.egg-info/not-zip-safe
module_B.egg-info/top_level.txt