Metadata-Version: 2.1
Name: module-B
Version: 1.4.0
Summary: Macrolib's description
Home-page: https://github.com/maite828/module_B.git
License: MIT
Download-URL: https://github.com/maite828/modlue_B/archive/refs/heads/main.zip
Platform: UNKNOWN
Requires-Python: >=3.6
